salome_med-4.1.1.dist-info/WHEEL
salome_med-4.1.1.dist-info/METADATA
salome_med-4.1.1.dist-info/RECORD
med/medsubdomain.py
med/_medprofile.so
med/_medfile.so
med/_medfamily.so
med/_medsubdomain.so
med/medlink.py
med/_medlink.so
med/medparameter.py
med/_medmesh.so
med/medfield.py
med/_medlocalization.so
med/medmesh.py
med/_medstructelement.so
med/__init__.py
med/_medenumtest.so
med/_medinterp.so
med/_medenum.so
med/_medparameter.so
med/medstructelement.py
med/_medlibrary.so
med/_medfilter.so
med/medinterp.py
med/medprofile.py
med/medenum.py
med/_medfield.so
med/medequivalence.py
med/medfile.py
med/medfamily.py
med/medfilter.py
med/medlibrary.py
med/medenumtest.py
med/medlocalization.py
med/_medequivalence.so
salome_med.libs/libmedC-63332a9f.so.11.1.1
salome_med.libs/libhdf5-554d4526.so.103.0.0
